MANIFEST.in
README.rst
lzf.py
lzf_build.py
setup.py
liblzf/bench.c
liblzf/config.h
liblzf/crc32.h
liblzf/lzf.c
liblzf/lzf.h
liblzf/lzfP.h
liblzf/lzf_c.c
liblzf/lzf_c_best.c
liblzf/lzf_d.c
lzf.egg-info/PKG-INFO
lzf.egg-info/SOURCES.txt
lzf.egg-info/dependency_links.txt
lzf.egg-info/entry_points.txt
lzf.egg-info/not-zip-safe
lzf.egg-info/requires.txt
lzf.egg-info/top_level.txt
vendor/liblzf/config.h
vendor/liblzf/lzf.c
vendor/liblzf/lzf.h
vendor/liblzf/lzfP.h
vendor/liblzf/lzf_c.c
vendor/liblzf/lzf_c_best.c
vendor/liblzf/lzf_d.c