Metadata-Version: 1.1
Name: lzf
Version: 0.1
Summary: CFFI-based Python binding for LZF stream compression
Home-page: https://github.com/lordmauve/lzf
Author: Daniel Pope
Author-email: mauve@mauveweb.co.uk
License: UNKNOWN
Platform: UNKNOWN
Classifier: Development Status :: 4 - Beta
Classifier: Intended Audience :: Developers
Classifier: Programming Language :: Python :: 2
Classifier: Programming Language :: Python :: 3
Classifier: License :: OSI Approved :: BSD License
Classifier: Topic :: System :: Archiving :: Compression
